tsalign-0.1.0.dist-info/METADATA
tsalign-0.1.0.dist-info/WHEEL
tsalign/__init__.py
tsalign/tsalign.cpython-312-x86_64-linux-gnu.so
tsalign-0.1.0.dist-info/RECORD
