Metadata-Version: 2.4
Name: tsalign
Version: 0.1.0
Classifier: Programming Language :: Rust
Classifier: Programming Language :: Python :: Implementation :: CPython
Classifier: Programming Language :: Python :: Implementation :: PyPy
Summary: Python Bindings for `lib_tsalign`
Author: Sebastian Schmidt <sebastian.schmidt@helsinki.fi>, Jasper Krauter <jasper.krauter@helsinki.fi>
Author-email: Sebastian Schmidt <sebastian.schmidt@helsinki.fi>, Jasper Krauter <jasper.krauter@helsinki.fi>
License: BSD-2-Clause
Requires-Python: >=3.8
Project-URL: Source Code, https://github.com/sebschmi/template-switch-aligner
